odoo/addons/website_crm_privacy_policy/README.rst
odoo/addons/website_crm_privacy_policy/__init__.py
odoo/addons/website_crm_privacy_policy/__manifest__.py
odoo/addons/website_crm_privacy_policy/i18n/ca.po
odoo/addons/website_crm_privacy_policy/i18n/de.po
odoo/addons/website_crm_privacy_policy/i18n/el_GR.po
odoo/addons/website_crm_privacy_policy/i18n/es.po
odoo/addons/website_crm_privacy_policy/i18n/fr.po
odoo/addons/website_crm_privacy_policy/i18n/it.po
odoo/addons/website_crm_privacy_policy/i18n/pt_BR.po
odoo/addons/website_crm_privacy_policy/i18n/ru.po
odoo/addons/website_crm_privacy_policy/i18n/sl.po
odoo/addons/website_crm_privacy_policy/static/description/icon.png
odoo/addons/website_crm_privacy_policy/templates/contactus.xml
odoo11_addon_website_crm_privacy_policy-11.0.1.0.0.dist-info/DESCRIPTION.rst
odoo11_addon_website_crm_privacy_policy-11.0.1.0.0.dist-info/METADATA
odoo11_addon_website_crm_privacy_policy-11.0.1.0.0.dist-info/RECORD
odoo11_addon_website_crm_privacy_policy-11.0.1.0.0.dist-info/WHEEL
odoo11_addon_website_crm_privacy_policy-11.0.1.0.0.dist-info/metadata.json
odoo11_addon_website_crm_privacy_policy-11.0.1.0.0.dist-info/top_level.txt
